maibobo-0.1.0.dist-info/METADATA
maibobo-0.1.0.dist-info/WHEEL
maibobo/__init__.py
maibobo/engine.py
maibobo-0.1.0.dist-info/RECORD
